tython/__init__.py
tython/interpreter.py
tython-0.0.1a0.dist-info/METADATA
tython-0.0.1a0.dist-info/WHEEL
tython-0.0.1a0.dist-info/top_level.txt
tython-0.0.1a0.dist-info/RECORD
